{"Camera":{"Position":{"x":25.0,"y":25.0,"z":5.0},"Rotation":{"x":0.298836231,"y":-0.640856445,"z":0.298836231,"w":0.640856445},"Scale":{"x":1.0,"y":1.0,"z":1.0}},"Resources":[{"Type":"Player1","Name":"Player1","Id":2,"Position":{"x":0.0,"y":0.0,"z":0.0},"Rotation":{"x":0.0,"y":0.0,"z":0.0,"w":1.0},"Scale":{"x":1.0,"y":1.0,"z":1.0},"HitPoints":0,"Attacking":false,"MovingIntoPosition":false,"Aiming":false,"AmountLeft":100.0},{"Type":"Player2","Name":"Player2","Id":6,"Position":{"x":0.0,"y":1.0,"z":0.0},"Rotation":{"x":0.0,"y":0.0,"z":0.0,"w":1.0},"Scale":{"x":1.0,"y":1.0,"z":1.0},"HitPoints":0,"Attacking":false,"MovingIntoPosition":false,"Aiming":false,"AmountLeft":100.0}],"Players":[{"Username":"Player1","Human":true,"TeamColor":{"r":1.0,"g":0.4764151,"b":0.884935,"a":0.0},"Resources":[]}]}